{
  "incumbent_ids": [
    1290
  ],
  "rejected_config_ids": [
    1,
    16,
    411,
    440,
    470,
    516,
    517,
    587,
    685,
    710,
    725,
    912
  ],
  "incumbents_changed": 13,
  "trajectory": [
    {
      "config_ids": [
        1
      ],
      "costs": [
        79.16631333159083
      ],
      "trial": 1,
      "walltime": 61.5183641910553
    },
    {
      "config_ids": [
        16
      ],
      "costs": [
        170.88335545766634
      ],
      "trial": 47,
      "walltime": 987.3214182853699
    },
    {
      "config_ids": [
        411
      ],
      "costs": [
        163.9916381650005
      ],
      "trial": 1232,
      "walltime": 22366.628336906433
    },
    {
      "config_ids": [
        440
      ],
      "costs": [
        156.26964481059804
      ],
      "trial": 1319,
      "walltime": 26801.22826576233
    },
    {
      "config_ids": [
        470
      ],
      "costs": [
        154.28550348570198
      ],
      "trial": 1409,
      "walltime": 31802.066084861755
    },
    {
      "config_ids": [
        516
      ],
      "costs": [
        153.3796892850054
      ],
      "trial": 1547,
      "walltime": 38368.88173866272
    },
    {
      "config_ids": [
        517
      ],
      "costs": [
        152.51088500409944
      ],
      "trial": 1550,
      "walltime": 38560.18179607391
    },
    {
      "config_ids": [
        587
      ],
      "costs": [
        150.39845229491743
      ],
      "trial": 1760,
      "walltime": 49107.74896430969
    },
    {
      "config_ids": [
        685
      ],
      "costs": [
        148.6548916191085
      ],
      "trial": 2054,
      "walltime": 64962.80519723892
    },
    {
      "config_ids": [
        710
      ],
      "costs": [
        148.34200941853308
      ],
      "trial": 2129,
      "walltime": 69024.15153431892
    },
    {
      "config_ids": [
        725
      ],
      "costs": [
        146.83668388755032
      ],
      "trial": 2174,
      "walltime": 70782.11455607414
    },
    {
      "config_ids": [
        912
      ],
      "costs": [
        146.58426841210368
      ],
      "trial": 2735,
      "walltime": 102606.81761622429
    },
    {
      "config_ids": [
        1290
      ],
      "costs": [
        146.56610361295847
      ],
      "trial": 3869,
      "walltime": 163956.3739361763
    }
  ],
  "state": {
    "queue": [
      [
        2001,
        1
      ]
    ]
  }
}